desiutil/__init__.py
desiutil/_version.py
desiutil/annotate.py
desiutil/api.py
desiutil/bitmask.py
desiutil/brick.py
desiutil/census.py
desiutil/depend.py
desiutil/dust.py
desiutil/funcfits.py
desiutil/git.py
desiutil/healpix.py
desiutil/iers.py
desiutil/install.py
desiutil/io.py
desiutil/log.py
desiutil/modules.py
desiutil/names.py
desiutil/plots.py
desiutil/redirect.py
desiutil/setup.py
desiutil/sklearn.py
desiutil/stats.py
desiutil/svn.py
desiutil/timer.py
desiutil/data/DES_footprint.txt
desiutil/data/Leap_Second.dat
desiutil/data/ReadMe.eopc04
desiutil/data/ReadMe.finals2000A
desiutil/data/census.yaml
desiutil/data/desiutil.module
desiutil/data/eopc04.1962-now
desiutil/data/finals2000A.all
desiutil/data/iers_frozen.ecsv
desiutil/test/__init__.py
desiutil/test/make_testmaps.py
desiutil/test/test_annotate.py
desiutil/test/test_api.py
desiutil/test/test_bitmask.py
desiutil/test/test_brick.py
desiutil/test/test_census.py
desiutil/test/test_depend.py
desiutil/test/test_dust.py
desiutil/test/test_funcfits.py
desiutil/test/test_git.py
desiutil/test/test_healpix.py
desiutil/test/test_iers.py
desiutil/test/test_install.py
desiutil/test/test_io.py
desiutil/test/test_log.py
desiutil/test/test_modules.py
desiutil/test/test_names.py
desiutil/test/test_plots.py
desiutil/test/test_redirect.py
desiutil/test/test_setup.py
desiutil/test/test_sklearn.py
desiutil/test/test_stats.py
desiutil/test/test_svn.py
desiutil/test/test_timer.py
desiutil/test/test_top_level.py
desiutil/test/t/SFD_dust_4096_ngp.fits
desiutil/test/t/SFD_dust_4096_sgp.fits
desiutil/test/t/generic_dependencies.txt
desiutil/test/t/qso_gmm.fits
desiutil/test/t/test.module
desiutil/test/t/test_fix_permissions.sh
desiutil-3.6.0.data/scripts/annotate_fits
desiutil-3.6.0.data/scripts/desiBootstrap.sh
desiutil-3.6.0.data/scripts/desiInstall
desiutil-3.6.0.data/scripts/desi_api_file
desiutil-3.6.0.data/scripts/desi_module_file
desiutil-3.6.0.data/scripts/desi_update_version
desiutil-3.6.0.data/scripts/fix_permissions.sh
desiutil-3.6.0.dist-info/licenses/LICENSE.rst
desiutil-3.6.0.dist-info/METADATA
desiutil-3.6.0.dist-info/WHEEL
desiutil-3.6.0.dist-info/top_level.txt
desiutil-3.6.0.dist-info/zip-safe
desiutil-3.6.0.dist-info/RECORD
