Metadata-Version: 2.4
Name: desiutil
Version: 3.6.0
Summary: DESI utilities package
Home-page: https://github.com/desihub/desiutil
Author: DESI Collaboration
Author-email: desi-data@desi.lbl.gov
License: BSD-3-Clause
Classifier: Development Status :: 5 - Production/Stable
Classifier: Environment :: Console
Classifier: Intended Audience :: Science/Research
Classifier: Operating System :: OS Independent
Classifier: Programming Language :: Python :: 3
Classifier: Topic :: Scientific/Engineering :: Astronomy
Classifier: Topic :: System :: Software Distribution
Classifier: Topic :: Utilities
Requires-Python: >=3.10
License-File: LICENSE.rst
Requires-Dist: requests
Requires-Dist: pyyaml
Requires-Dist: astropy
Provides-Extra: all
Requires-Dist: healpy; extra == "all"
Requires-Dist: matplotlib; extra == "all"
Requires-Dist: scipy; extra == "all"
Requires-Dist: speclite; extra == "all"
Provides-Extra: test
Requires-Dist: desiutil[all]; extra == "test"
Requires-Dist: pytest; extra == "test"
Provides-Extra: coverage
Requires-Dist: desiutil[all]; extra == "coverage"
Requires-Dist: pytest-cov; extra == "coverage"
Requires-Dist: coveralls; extra == "coverage"
Provides-Extra: doc
Requires-Dist: Sphinx; extra == "doc"
Requires-Dist: sphinx-rtd-theme; extra == "doc"
Dynamic: license-file
